{
  "attempted_this_run": 120,
  "cached_selected_this_run": 0,
  "catalog_games": 743,
  "catalog_games_in_scope": 50,
  "catalog_limit": 50,
  "catalog_offset": 425,
  "cdx_games_considered": 50,
  "cdx_rows": 174,
  "cdx_urls_cached": 6,
  "cdx_urls_failed": 20,
  "cdx_urls_fetched": 30,
  "collapse": "",
  "failed_this_run": 2,
  "fetched_this_run": 118,
  "first_history_date": "2013-09-18",
  "games_with_history": 119,
  "history_rows": 1551,
  "known_failures": 177,
  "last_history_date": "2025-10-25",
  "manifest_entries": 1551,
  "metrics_jobs": 171,
  "pending_before_run": 145,
  "run_timestamp": "2026-06-29T06:45:40Z",
  "schemes": [
    "http",
    "https"
  ]
}